vhwebscan/__init__.py
vhwebscan/config.py
vhwebscan/render.py
vhwebscan/role.py
vhwebscan/style.py
vhwebscan/tag.py
vhwebscan/webscan.py
vhwebscan/atw/__init__.py
vhwebscan/atw/blockblank.py
vhwebscan/atw/button.py
vhwebscan/atw/format.py
vhwebscan/atw/frameblank.py
vhwebscan/atw/image.py
vhwebscan/atw/input.py
vhwebscan/atw/menu.py
vhwebscan/atw/text.py
vhwebscan-0.2.dist-info/METADATA
vhwebscan-0.2.dist-info/WHEEL
vhwebscan-0.2.dist-info/top_level.txt
vhwebscan-0.2.dist-info/RECORD
