Metadata-Version: 2.1
Name: vhwebscan
Version: 0.2
Summary: Viethas Website Tool Scan
Requires-Python: >=3.8
Requires-Dist: beautifulsoup4>=4.12
Requires-Dist: certifi
Requires-Dist: selenium>=4.20
Requires-Dist: sniffio
Requires-Dist: tinycss2
